attribute/__init__.py
attribute/api.py
tombulled_attribute-0.1.5.dist-info/LICENSE
tombulled_attribute-0.1.5.dist-info/WHEEL
tombulled_attribute-0.1.5.dist-info/METADATA
tombulled_attribute-0.1.5.dist-info/RECORD
