Metadata-Version: 2.1
Name: tombulled-attribute
Version: 0.1.5
Summary: Attribute management made easy
Home-page: https://github.com/tombulled/attribute
License: MIT
Keywords: python,attribute
Author: Tom Bulled
Author-email: 26026015+tombulled@users.noreply.github.com
Requires-Python: >=3.8,<4.0
Classifier: License :: OSI Approved :: MIT License
Classifier: Programming Language :: Python :: 3
Classifier: Programming Language :: Python :: 3.10
Classifier: Programming Language :: Python :: 3.8
Classifier: Programming Language :: Python :: 3.9
Project-URL: Repository, https://github.com/tombulled/attribute
